cloudshell/__init__.py
cloudshell/shell/__init__.py
cloudshell/shell/standards/__init__.py
cloudshell/shell/standards/firewall/__init__.py
cloudshell/shell/standards/firewall/autoload_model.py
cloudshell/shell/standards/firewall/driver_interface.py
cloudshell/shell/standards/firewall/resource_config.py
tests/__init__.py
tests/cloudshell/__init__.py
tests/cloudshell/conftest.py
tests/cloudshell/shell/__init__.py
tests/cloudshell/shell/standards/__init__.py
tests/cloudshell/shell/standards/firewall/__init__.py
tests/cloudshell/shell/standards/firewall/test_autoload_model.py
tests/cloudshell/shell/standards/firewall/test_driver_interface.py
tests/cloudshell/shell/standards/firewall/test_resource_ config.py
cloudshell_shell_firewall_standard-4.0.0.dist-info/METADATA
cloudshell_shell_firewall_standard-4.0.0.dist-info/WHEEL
cloudshell_shell_firewall_standard-4.0.0.dist-info/top_level.txt
cloudshell_shell_firewall_standard-4.0.0.dist-info/RECORD
