Metadata-Version: 2.1
Name: cloudshell-shell-firewall-standard
Version: 4.0.0
Summary: QualiSystems Shells Firewall Standard Package
Home-page: https://www.quali.com/
Author: Quali
Author-email: info@quali.com
Requires-Python: ~=3.7
Requires-Dist: cloudshell-shell-standards (~=2.0)
Requires-Dist: attrs (>=21)
